dan/__init__.py
tests/fixtures/__init__.py
tests/strategies/__init__.py
dan-0.0.0.dist-info/LICENSE
dan-0.0.0.dist-info/METADATA
dan-0.0.0.dist-info/WHEEL
dan-0.0.0.dist-info/top_level.txt
dan-0.0.0.dist-info/RECORD
