Metadata-Version: 2.1
Name: dan
Version: 0.0.0
Summary: Data analyzer.
Home-page: https://github.com/lycantropos/dan/
Author: Azat Ibrakov
Author-email: azatibrakov@gmail.com
License: UNKNOWN
Download-URL: https://github.com/lycantropos/dan/archive/master.zip
Platform: UNKNOWN
Requires-Python: >=3.5
